lescode/__init__.py
lescode/cache/__init__.py
lescode/cache/cache.py
lescode/cache/policies.py
lescode/cache/types.py
lescode/config/__init__.py
lescode/config/pool.py
lescode/export/__init__.py
lescode/export/exporter.py
lescode/functional/__init__.py
lescode/functional/plugin.py
lescode/functional/pattern/__init__.py
lescode/functional/pattern/pattern.py
lescode/functional/pattern/types.py
lescode/functional/tools/__init__.py
lescode/functional/tools/functional.py
lescode/logger/__init__.py
lescode/logger/logger.py
lescode/namespace/__init__.py
lescode/namespace/namespace.py
lescode/parser/__init__.py
lescode/parser/basic.py
lescode/patterns/__init__.py
lescode/patterns/behavioral/__init__.py
lescode/patterns/behavioral/chain.py
lescode/patterns/creational/__init__.py
lescode/patterns/creational/object_pool.py
lescode/patterns/creational/singleton.py
lescode/patterns/structural/__init__.py
lescode/patterns/structural/registry.py
lescode/scheduler/__init__.py
lescode/scheduler/scheduler.py
lescode/scheduler/time.py
lescode/scheduler/types.py
lescode/types/__init__.py
lescode/types/base.py
lescode-0.2.13.dist-info/LICENSE.txt
lescode-0.2.13.dist-info/METADATA
lescode-0.2.13.dist-info/WHEEL
lescode-0.2.13.dist-info/top_level.txt
lescode-0.2.13.dist-info/RECORD
