Metadata-Version: 2.1
Name: lescode
Version: 0.2.13
Summary: lescode
Home-page: https://github.com/NgHoangDat/lescode.git
Download-URL: https://github.com/NgHoangDat/lescode/archive/v0.2.13.tar.gz
Author: nghoangdat
Author-email: 18.hoang.dat.12@gmail.com
License: UNKNOWN
Platform: UNKNOWN
Classifier: Programming Language :: Python :: 3
Classifier: License :: OSI Approved :: MIT License
Classifier: Operating System :: OS Independent
Requires-Python: >=3.6
License-File: LICENSE.txt
Requires-Dist: msgpack
Requires-Dist: python-dateutil
Requires-Dist: pyyaml
Requires-Dist: toolz
Requires-Dist: dataclasses ; python_version == "3.6"
Provides-Extra: dev
Requires-Dist: black ; extra == 'dev'
Requires-Dist: jupyter ; extra == 'dev'
